Workbook

Sheet Settings
A1: RB v1.1 settings (edit the yellow cells)
A3: Current equity ($) | B3: 100000
A4: Risk per trade (% of equity) | B4: 0.0025
A5: Investment cap per ticker ($) | B5: 20000
A6: Target (R multiple) | B6: 2
A7: Minimum buffer ($) | B7: 0.01
A8: Buffer (% of signal high/low) | B8: 0.0002
A9: Minimum stop (ATR multiple) | B9: 1
A11: Dollar risk per trade ($R, a maximum) | B11: =B3*B4
A12: Hard rules (any fail = do not trade): LONG C>O / SHORT C<O; 09:45 <= time < 15:30 ET; last completed 15m Close vs EMA20;
A13: not stale (10 min); not chased (> 0.25 ATR past entry); price not through the stop; one position/order per ticker.

Sheet Journal
A1: Trade ID | B1: Date | C1: Entry time | D1: Ticker | E1: Direction | F1: Alert time | G1: Exit time | H1: Signal high | I1: Signal low | J1: Buffer | K1: Planned entry | L1: Actual entry (fill) | M1: Stop | N1: Equity at entry | O1: R (risk/share) | P1: $R budget | Q1: Shares (min of risk & cap) | R1: Planned $ risk | S1: Target (2R) | T1: Exit price | U1: Exit reason | V1: P/L $ | W1: P/L % equity | X1: R result | Y1: Entry slippage $/sh | Z1: MFE (R) | AA1: MAE (R) | AB1: R at 30 min | AC1: Opportunity score /100 | AD1: RVOL | AE1: RSI | AF1: VWAP dist (ATR) | AG1: EMA alignment / sep | AH1: 15m confirm | AI1: Screenshot before | AJ1: Screenshot after | AK1: Market regime | AL1: News catalyst? | AM1: Followed rules? | AN1: Mistake | AO1: Notes | AP1: ATR(14) 5m | AQ1: Opportunity tier
J2: =IF($E2="","",MAX(Settings!$B$7,ROUND(Settings!$B$8*IF($E2="LONG",H2,I2),2))) | K2: =IF($E2="","",IF($E2="LONG",H2+J2,I2-J2)) | M2: =IF($E2="","",IF($E2="LONG",K2-O2,K2+O2)) | O2: =IF(OR($E2="",AP2=""),"",ROUNDUP(ROUND(MAX(IF($E2="LONG",K2-I2,H2-K2),Settings!$B$9*AP2),6),2)) | P2: =IF($E2="","",N2*Settings!$B$4) | Q2: =IF(O2="","",MIN(INT(ROUND(P2/O2,6)),INT(ROUND(Settings!$B$5/K2,6)))) | R2: =IF(O2="","",Q2*O2) | S2: =IF(O2="","",IF($E2="LONG",K2+Settings!$B$6*O2,K2-Settings!$B$6*O2)) | V2: =IF(OR($E2="",T2=""),"",IF($E2="LONG",(T2-L2)*Q2,(L2-T2)*Q2)) | W2: =IF(V2="","",V2/N2) | X2: =IF(V2="","",V2/R2) | Y2: =IF(OR($E2="",L2=""),"",IF($E2="LONG",L2-K2,K2-L2))
J3: =IF($E3="","",MAX(Settings!$B$7,ROUND(Settings!$B$8*IF($E3="LONG",H3,I3),2))) | K3: =IF($E3="","",IF($E3="LONG",H3+J3,I3-J3)) | M3: =IF($E3="","",IF($E3="LONG",K3-O3,K3+O3)) | O3: =IF(OR($E3="",AP3=""),"",ROUNDUP(ROUND(MAX(IF($E3="LONG",K3-I3,H3-K3),Settings!$B$9*AP3),6),2)) | P3: =IF($E3="","",N3*Settings!$B$4) | Q3: =IF(O3="","",MIN(INT(ROUND(P3/O3,6)),INT(ROUND(Settings!$B$5/K3,6)))) | R3: =IF(O3="","",Q3*O3) | S3: =IF(O3="","",IF($E3="LONG",K3+Settings!$B$6*O3,K3-Settings!$B$6*O3)) | V3: =IF(OR($E3="",T3=""),"",IF($E3="LONG",(T3-L3)*Q3,(L3-T3)*Q3)) | W3: =IF(V3="","",V3/N3) | X3: =IF(V3="","",V3/R3) | Y3: =IF(OR($E3="",L3=""),"",IF($E3="LONG",L3-K3,K3-L3))
J4: =IF($E4="","",MAX(Settings!$B$7,ROUND(Settings!$B$8*IF($E4="LONG",H4,I4),2))) | K4: =IF($E4="","",IF($E4="LONG",H4+J4,I4-J4)) | M4: =IF($E4="","",IF($E4="LONG",K4-O4,K4+O4)) | O4: =IF(OR($E4="",AP4=""),"",ROUNDUP(ROUND(MAX(IF($E4="LONG",K4-I4,H4-K4),Settings!$B$9*AP4),6),2)) | P4: =IF($E4="","",N4*Settings!$B$4) | Q4: =IF(O4="","",MIN(INT(ROUND(P4/O4,6)),INT(ROUND(Settings!$B$5/K4,6)))) | R4: =IF(O4="","",Q4*O4) | S4: =IF(O4="","",IF($E4="LONG",K4+Settings!$B$6*O4,K4-Settings!$B$6*O4)) | V4: =IF(OR($E4="",T4=""),"",IF($E4="LONG",(T4-L4)*Q4,(L4-T4)*Q4)) | W4: =IF(V4="","",V4/N4) | X4: =IF(V4="","",V4/R4) | Y4: =IF(OR($E4="",L4=""),"",IF($E4="LONG",L4-K4,K4-L4))
J5: =IF($E5="","",MAX(Settings!$B$7,ROUND(Settings!$B$8*IF($E5="LONG",H5,I5),2))) | K5: =IF($E5="","",IF($E5="LONG",H5+J5,I5-J5)) | M5: =IF($E5="","",IF($E5="LONG",K5-O5,K5+O5)) | O5: =IF(OR($E5="",AP5=""),"",ROUNDUP(ROUND(MAX(IF($E5="LONG",K5-I5,H5-K5),Settings!$B$9*AP5),6),2)) | P5: =IF($E5="","",N5*Settings!$B$4) | Q5: =IF(O5="","",MIN(INT(ROUND(P5/O5,6)),INT(ROUND(Settings!$B$5/K5,6)))) | R5: =IF(O5="","",Q5*O5) | S5: =IF(O5="","",IF($E5="LONG",K5+Settings!$B$6*O5,K5-Settings!$B$6*O5)) | V5: =IF(OR($E5="",T5=""),"",IF($E5="LONG",(T5-L5)*Q5,(L5-T5)*Q5)) | W5: =IF(V5="","",V5/N5) | X5: =IF(V5="","",V5/R5) | Y5: =IF(OR($E5="",L5=""),"",IF($E5="LONG",L5-K5,K5-L5))
J6: =IF($E6="","",MAX(Settings!$B$7,ROUND(Settings!$B$8*IF($E6="LONG",H6,I6),2))) | K6: =IF($E6="","",IF($E6="LONG",H6+J6,I6-J6)) | M6: =IF($E6="","",IF($E6="LONG",K6-O6,K6+O6)) | O6: =IF(OR($E6="",AP6=""),"",ROUNDUP(ROUND(MAX(IF($E6="LONG",K6-I6,H6-K6),Settings!$B$9*AP6),6),2)) | P6: =IF($E6="","",N6*Settings!$B$4) | Q6: =IF(O6="","",MIN(INT(ROUND(P6/O6,6)),INT(ROUND(Settings!$B$5/K6,6)))) | R6: =IF(O6="","",Q6*O6) | S6: =IF(O6="","",IF($E6="LONG",K6+Settings!$B$6*O6,K6-Settings!$B$6*O6)) | V6: =IF(OR($E6="",T6=""),"",IF($E6="LONG",(T6-L6)*Q6,(L6-T6)*Q6)) | W6: =IF(V6="","",V6/N6) | X6: =IF(V6="","",V6/R6) | Y6: =IF(OR($E6="",L6=""),"",IF($E6="LONG",L6-K6,K6-L6))
J7: =IF($E7="","",MAX(Settings!$B$7,ROUND(Settings!$B$8*IF($E7="LONG",H7,I7),2))) | K7: =IF($E7="","",IF($E7="LONG",H7+J7,I7-J7)) | M7: =IF($E7="","",IF($E7="LONG",K7-O7,K7+O7)) | O7: =IF(OR($E7="",AP7=""),"",ROUNDUP(ROUND(MAX(IF($E7="LONG",K7-I7,H7-K7),Settings!$B$9*AP7),6),2)) | P7: =IF($E7="","",N7*Settings!$B$4) | Q7: =IF(O7="","",MIN(INT(ROUND(P7/O7,6)),INT(ROUND(Settings!$B$5/K7,6)))) | R7: =IF(O7="","",Q7*O7) | S7: =IF(O7="","",IF($E7="LONG",K7+Settings!$B$6*O7,K7-Settings!$B$6*O7)) | V7: =IF(OR($E7="",T7=""),"",IF($E7="LONG",(T7-L7)*Q7,(L7-T7)*Q7)) | W7: =IF(V7="","",V7/N7) | X7: =IF(V7="","",V7/R7) | Y7: =IF(OR($E7="",L7=""),"",IF($E7="LONG",L7-K7,K7-L7))
J8: =IF($E8="","",MAX(Settings!$B$7,ROUND(Settings!$B$8*IF($E8="LONG",H8,I8),2))) | K8: =IF($E8="","",IF($E8="LONG",H8+J8,I8-J8)) | M8: =IF($E8="","",IF($E8="LONG",K8-O8,K8+O8)) | O8: =IF(OR($E8="",AP8=""),"",ROUNDUP(ROUND(MAX(IF($E8="LONG",K8-I8,H8-K8),Settings!$B$9*AP8),6),2)) | P8: =IF($E8="","",N8*Settings!$B$4) | Q8: =IF(O8="","",MIN(INT(ROUND(P8/O8,6)),INT(ROUND(Settings!$B$5/K8,6)))) | R8: =IF(O8="","",Q8*O8) | S8: =IF(O8="","",IF($E8="LONG",K8+Settings!$B$6*O8,K8-Settings!$B$6*O8)) | V8: =IF(OR($E8="",T8=""),"",IF($E8="LONG",(T8-L8)*Q8,(L8-T8)*Q8)) | W8: =IF(V8="","",V8/N8) | X8: =IF(V8="","",V8/R8) | Y8: =IF(OR($E8="",L8=""),"",IF($E8="LONG",L8-K8,K8-L8))
J9: =IF($E9="","",MAX(Settings!$B$7,ROUND(Settings!$B$8*IF($E9="LONG",H9,I9),2))) | K9: =IF($E9="","",IF($E9="LONG",H9+J9,I9-J9)) | M9: =IF($E9="","",IF($E9="LONG",K9-O9,K9+O9)) | O9: =IF(OR($E9="",AP9=""),"",ROUNDUP(ROUND(MAX(IF($E9="LONG",K9-I9,H9-K9),Settings!$B$9*AP9),6),2)) | P9: =IF($E9="","",N9*Settings!$B$4) | Q9: =IF(O9="","",MIN(INT(ROUND(P9/O9,6)),INT(ROUND(Settings!$B$5/K9,6)))) | R9: =IF(O9="","",Q9*O9) | S9: =IF(O9="","",IF($E9="LONG",K9+Settings!$B$6*O9,K9-Settings!$B$6*O9)) | V9: =IF(OR($E9="",T9=""),"",IF($E9="LONG",(T9-L9)*Q9,(L9-T9)*Q9)) | W9: =IF(V9="","",V9/N9) | X9: =IF(V9="","",V9/R9) | Y9: =IF(OR($E9="",L9=""),"",IF($E9="LONG",L9-K9,K9-L9))
J10: =IF($E10="","",MAX(Settings!$B$7,ROUND(Settings!$B$8*IF($E10="LONG",H10,I10),2))) | K10: =IF($E10="","",IF($E10="LONG",H10+J10,I10-J10)) | M10: =IF($E10="","",IF($E10="LONG",K10-O10,K10+O10)) | O10: =IF(OR($E10="",AP10=""),"",ROUNDUP(ROUND(MAX(IF($E10="LONG",K10-I10,H10-K10),Settings!$B$9*AP10),6),2)) | P10: =IF($E10="","",N10*Settings!$B$4) | Q10: =IF(O10="","",MIN(INT(ROUND(P10/O10,6)),INT(ROUND(Settings!$B$5/K10,6)))) | R10: =IF(O10="","",Q10*O10) | S10: =IF(O10="","",IF($E10="LONG",K10+Settings!$B$6*O10,K10-Settings!$B$6*O10)) | V10: =IF(OR($E10="",T10=""),"",IF($E10="LONG",(T10-L10)*Q10,(L10-T10)*Q10)) | W10: =IF(V10="","",V10/N10) | X10: =IF(V10="","",V10/R10) | Y10: =IF(OR($E10="",L10=""),"",IF($E10="LONG",L10-K10,K10-L10))
J11: =IF($E11="","",MAX(Settings!$B$7,ROUND(Settings!$B$8*IF($E11="LONG",H11,I11),2))) | K11: =IF($E11="","",IF($E11="LONG",H11+J11,I11-J11)) | M11: =IF($E11="","",IF($E11="LONG",K11-O11,K11+O11)) | O11: =IF(OR($E11="",AP11=""),"",ROUNDUP(ROUND(MAX(IF($E11="LONG",K11-I11,H11-K11),Settings!$B$9*AP11),6),2)) | P11: =IF($E11="","",N11*Settings!$B$4) | Q11: =IF(O11="","",MIN(INT(ROUND(P11/O11,6)),INT(ROUND(Settings!$B$5/K11,6)))) | R11: =IF(O11="","",Q11*O11) | S11: =IF(O11="","",IF($E11="LONG",K11+Settings!$B$6*O11,K11-Settings!$B$6*O11)) | V11: =IF(OR($E11="",T11=""),"",IF($E11="LONG",(T11-L11)*Q11,(L11-T11)*Q11)) | W11: =IF(V11="","",V11/N11) | X11: =IF(V11="","",V11/R11) | Y11: =IF(OR($E11="",L11=""),"",IF($E11="LONG",L11-K11,K11-L11))
J12: =IF($E12="","",MAX(Settings!$B$7,ROUND(Settings!$B$8*IF($E12="LONG",H12,I12),2))) | K12: =IF($E12="","",IF($E12="LONG",H12+J12,I12-J12)) | M12: =IF($E12="","",IF($E12="LONG",K12-O12,K12+O12)) | O12: =IF(OR($E12="",AP12=""),"",ROUNDUP(ROUND(MAX(IF($E12="LONG",K12-I12,H12-K12),Settings!$B$9*AP12),6),2)) | P12: =IF($E12="","",N12*Settings!$B$4) | Q12: =IF(O12="","",MIN(INT(ROUND(P12/O12,6)),INT(ROUND(Settings!$B$5/K12,6)))) | R12: =IF(O12="","",Q12*O12) | S12: =IF(O12="","",IF($E12="LONG",K12+Settings!$B$6*O12,K12-Settings!$B$6*O12)) | V12: =IF(OR($E12="",T12=""),"",IF($E12="LONG",(T12-L12)*Q12,(L12-T12)*Q12)) | W12: =IF(V12="","",V12/N12) | X12: =IF(V12="","",V12/R12) | Y12: =IF(OR($E12="",L12=""),"",IF($E12="LONG",L12-K12,K12-L12))
J13: =IF($E13="","",MAX(Settings!$B$7,ROUND(Settings!$B$8*IF($E13="LONG",H13,I13),2))) | K13: =IF($E13="","",IF($E13="LONG",H13+J13,I13-J13)) | M13: =IF($E13="","",IF($E13="LONG",K13-O13,K13+O13)) | O13: =IF(OR($E13="",AP13=""),"",ROUNDUP(ROUND(MAX(IF($E13="LONG",K13-I13,H13-K13),Settings!$B$9*AP13),6),2)) | P13: =IF($E13="","",N13*Settings!$B$4) | Q13: =IF(O13="","",MIN(INT(ROUND(P13/O13,6)),INT(ROUND(Settings!$B$5/K13,6)))) | R13: =IF(O13="","",Q13*O13) | S13: =IF(O13="","",IF($E13="LONG",K13+Settings!$B$6*O13,K13-Settings!$B$6*O13)) | V13: =IF(OR($E13="",T13=""),"",IF($E13="LONG",(T13-L13)*Q13,(L13-T13)*Q13)) | W13: =IF(V13="","",V13/N13) | X13: =IF(V13="","",V13/R13) | Y13: =IF(OR($E13="",L13=""),"",IF($E13="LONG",L13-K13,K13-L13))
... J501: =IF($E501="","",MAX(Settings!$B$7,ROUND(Settings!$B$8*IF($E501="LONG",H501,I501),2))) | K501: =IF($E501="","",IF($E501="LONG",H501+J501,I501-J501)) | M501: =IF($E501="","",IF($E501="LONG",K501-O501,K501+O501)) | O501: =IF(OR($E501="",AP501=""),"",ROUNDUP(ROUND(MAX(IF($E501="LONG",K501-I501,H501-K501),Settings!$B$9*AP501),6),2)) | P501: =IF($E501="","",N501*Settings!$B$4) | Q501: =IF(O501="","",MIN(INT(ROUND(P501/O501,6)),INT(ROUND(Settings!$B$5/K501,6)))) | R501: =IF(O501="","",Q501*O501) | S501: =IF(O501="","",IF($E501="LONG",K501+Settings!$B$6*O501,K501-Settings!$B$6*O501)) | V501: =IF(OR($E501="",T501=""),"",IF($E501="LONG",(T501-L501)*Q501,(L501-T501)*Q501)) | W501: =IF(V501="","",V501/N501) | X501: =IF(V501="","",V501/R501) | Y501: =IF(OR($E501="",L501=""),"",IF($E501="LONG",L501-K501,K501-L501))

Sheet Stats
A1: RB v1 performance (Chapter 40) | D1: Cum R | E1: Peak | F1: Drawdown
D2: =IF(Journal!X2="","",SUM(Journal!$X$2:X2)) | E2: =IF(D2="","",MAX(0,MAX($D$2:D2))) | F2: =IF(D2="","",E2-D2)
A3: Trades (closed) | B3: =COUNT(Journal!X2:X501) | D3: =IF(Journal!X3="","",SUM(Journal!$X$2:X3)) | E3: =IF(D3="","",MAX(0,MAX($D$2:D3))) | F3: =IF(D3="","",E3-D3)
A4: Wins | B4: =COUNTIF(Journal!X2:X501,">0") | D4: =IF(Journal!X4="","",SUM(Journal!$X$2:X4)) | E4: =IF(D4="","",MAX(0,MAX($D$2:D4))) | F4: =IF(D4="","",E4-D4)
A5: Losses | B5: =COUNTIF(Journal!X2:X501,"<=0") | D5: =IF(Journal!X5="","",SUM(Journal!$X$2:X5)) | E5: =IF(D5="","",MAX(0,MAX($D$2:D5))) | F5: =IF(D5="","",E5-D5)
A6: Win rate | B6: =IFERROR(B4/B3,0) | D6: =IF(Journal!X6="","",SUM(Journal!$X$2:X6)) | E6: =IF(D6="","",MAX(0,MAX($D$2:D6))) | F6: =IF(D6="","",E6-D6)
A7: Loss rate | B7: =IFERROR(B5/B3,0) | D7: =IF(Journal!X7="","",SUM(Journal!$X$2:X7)) | E7: =IF(D7="","",MAX(0,MAX($D$2:D7))) | F7: =IF(D7="","",E7-D7)
A8: Average winner (R) | B8: =IFERROR(AVERAGEIF(Journal!X2:X501,">0"),0) | D8: =IF(Journal!X8="","",SUM(Journal!$X$2:X8)) | E8: =IF(D8="","",MAX(0,MAX($D$2:D8))) | F8: =IF(D8="","",E8-D8)
A9: Average loser (R) | B9: =IFERROR(AVERAGEIF(Journal!X2:X501,"<=0"),0) | D9: =IF(Journal!X9="","",SUM(Journal!$X$2:X9)) | E9: =IF(D9="","",MAX(0,MAX($D$2:D9))) | F9: =IF(D9="","",E9-D9)
A10: Payoff ratio | B10: =IFERROR(B8/ABS(B9),0) | D10: =IF(Journal!X10="","",SUM(Journal!$X$2:X10)) | E10: =IF(D10="","",MAX(0,MAX($D$2:D10))) | F10: =IF(D10="","",E10-D10)
A11: Expectancy (R/trade) | B11: =B6*B8-B7*ABS(B9) | D11: =IF(Journal!X11="","",SUM(Journal!$X$2:X11)) | E11: =IF(D11="","",MAX(0,MAX($D$2:D11))) | F11: =IF(D11="","",E11-D11)
A12: Total R | B12: =SUM(Journal!X2:X501) | D12: =IF(Journal!X12="","",SUM(Journal!$X$2:X12)) | E12: =IF(D12="","",MAX(0,MAX($D$2:D12))) | F12: =IF(D12="","",E12-D12)
A13: Total P/L ($) | B13: =SUM(Journal!V2:V501) | D13: =IF(Journal!X13="","",SUM(Journal!$X$2:X13)) | E13: =IF(D13="","",MAX(0,MAX($D$2:D13))) | F13: =IF(D13="","",E13-D13)
A14: Profit factor | B14: =IFERROR(SUMIF(Journal!X2:X501,">0")/ABS(SUMIF(Journal!X2:X501,"<0")),0) | D14: =IF(Journal!X14="","",SUM(Journal!$X$2:X14)) | E14: =IF(D14="","",MAX(0,MAX($D$2:D14))) | F14: =IF(D14="","",E14-D14)
A15: Rules followed % | B15: =IFERROR(COUNTIF(Journal!AM2:AM501,"Y")/COUNTA(Journal!AM2:AM501),0) | D15: =IF(Journal!X15="","",SUM(Journal!$X$2:X15)) | E15: =IF(D15="","",MAX(0,MAX($D$2:D15))) | F15: =IF(D15="","",E15-D15)
A16: LONG expectancy (R) | B16: =IFERROR(AVERAGEIF(Journal!E2:E501,"LONG",Journal!X2:X501),0) | D16: =IF(Journal!X16="","",SUM(Journal!$X$2:X16)) | E16: =IF(D16="","",MAX(0,MAX($D$2:D16))) | F16: =IF(D16="","",E16-D16)
A17: SHORT expectancy (R) | B17: =IFERROR(AVERAGEIF(Journal!E2:E501,"SHORT",Journal!X2:X501),0) | D17: =IF(Journal!X17="","",SUM(Journal!$X$2:X17)) | E17: =IF(D17="","",MAX(0,MAX($D$2:D17))) | F17: =IF(D17="","",E17-D17)
A18: Average entry slippage ($/sh) | B18: =IFERROR(AVERAGE(Journal!Y2:Y501),0) | D18: =IF(Journal!X18="","",SUM(Journal!$X$2:X18)) | E18: =IF(D18="","",MAX(0,MAX($D$2:D18))) | F18: =IF(D18="","",E18-D18)
A19: Max drawdown (R) | B19: =IFERROR(MAX(Stats!F2:F501),0) | D19: =IF(Journal!X19="","",SUM(Journal!$X$2:X19)) | E19: =IF(D19="","",MAX(0,MAX($D$2:D19))) | F19: =IF(D19="","",E19-D19)
D20: =IF(Journal!X20="","",SUM(Journal!$X$2:X20)) | E20: =IF(D20="","",MAX(0,MAX($D$2:D20))) | F20: =IF(D20="","",E20-D20)
A21: Interpretation: see Chapter 40. Fewer than 50 trades = workflow data only. | D21: =IF(Journal!X21="","",SUM(Journal!$X$2:X21)) | E21: =IF(D21="","",MAX(0,MAX($D$2:D21))) | F21: =IF(D21="","",E21-D21)
D22: =IF(Journal!X22="","",SUM(Journal!$X$2:X22)) | E22: =IF(D22="","",MAX(0,MAX($D$2:D22))) | F22: =IF(D22="","",E22-D22)
D23: =IF(Journal!X23="","",SUM(Journal!$X$2:X23)) | E23: =IF(D23="","",MAX(0,MAX($D$2:D23))) | F23: =IF(D23="","",E23-D23)
D24: =IF(Journal!X24="","",SUM(Journal!$X$2:X24)) | E24: =IF(D24="","",MAX(0,MAX($D$2:D24))) | F24: =IF(D24="","",E24-D24)
D25: =IF(Journal!X25="","",SUM(Journal!$X$2:X25)) | E25: =IF(D25="","",MAX(0,MAX($D$2:D25))) | F25: =IF(D25="","",E25-D25)
D26: =IF(Journal!X26="","",SUM(Journal!$X$2:X26)) | E26: =IF(D26="","",MAX(0,MAX($D$2:D26))) | F26: =IF(D26="","",E26-D26)
D27: =IF(Journal!X27="","",SUM(Journal!$X$2:X27)) | E27: =IF(D27="","",MAX(0,MAX($D$2:D27))) | F27: =IF(D27="","",E27-D27)
D28: =IF(Journal!X28="","",SUM(Journal!$X$2:X28)) | E28: =IF(D28="","",MAX(0,MAX($D$2:D28))) | F28: =IF(D28="","",E28-D28)
D29: =IF(Journal!X29="","",SUM(Journal!$X$2:X29)) | E29: =IF(D29="","",MAX(0,MAX($D$2:D29))) | F29: =IF(D29="","",E29-D29)
D30: =IF(Journal!X30="","",SUM(Journal!$X$2:X30)) | E30: =IF(D30="","",MAX(0,MAX($D$2:D30))) | F30: =IF(D30="","",E30-D30)
D31: =IF(Journal!X31="","",SUM(Journal!$X$2:X31)) | E31: =IF(D31="","",MAX(0,MAX($D$2:D31))) | F31: =IF(D31="","",E31-D31)
D32: =IF(Journal!X32="","",SUM(Journal!$X$2:X32)) | E32: =IF(D32="","",MAX(0,MAX($D$2:D32))) | F32: =IF(D32="","",E32-D32)
D33: =IF(Journal!X33="","",SUM(Journal!$X$2:X33)) | E33: =IF(D33="","",MAX(0,MAX($D$2:D33))) | F33: =IF(D33="","",E33-D33)
... D501: =IF(Journal!X501="","",SUM(Journal!$X$2:X501)) | E501: =IF(D501="","",MAX(0,MAX($D$2:D501))) | F501: =IF(D501="","",E501-D501)

Sheet Sizer
A1: Quick position sizer, RB v1.1 (Chapter 37)
A3: Direction (LONG/SHORT) | B3: LONG
A4: Signal high | B4: 255.6
A5: Signal low | B5: 255.24
A6: ATR(14) 5m | B6: 0.37
A7: Buffer | B7: =MAX(Settings!B7,ROUND(Settings!B8*IF(B3="LONG",B4,B5),2))
A8: Entry (E) | B8: =IF(B3="LONG",B4+B7,B5-B7)
A9: R = MAX(structural, 1 ATR) | B9: =ROUNDUP(ROUND(MAX(IF(B3="LONG",B8-B5,B4-B8),Settings!B9*B6),6),2)
A10: Stop | B10: =IF(B3="LONG",B8-B9,B8+B9)
A11: $R | B11: =Settings!B11
A12: Shares by risk | B12: =INT(ROUND(B11/B9,6))
A13: Shares by cap | B13: =INT(ROUND(Settings!B5/B8,6))
A14: QUANTITY | B14: =MIN(B12,B13)
A15: Planned $ loss | B15: =B14*B9
A16: Target (2R) | B16: =IF(B3="LONG",B8+Settings!B6*B9,B8-Settings!B6*B9)
A17: Position value | B17: =B14*B8
A19: IBM example: E 255.65, R 0.41, stop 255.24, target 256.47, 78 shares. Check the hard rules first (Chapter 16).
